{
  "dependencies": [
    {
      "name": "@aws-sdk/client-schemas",
      "type": "build"
    },
    {
      "name": "@stylistic/eslint-plugin",
      "version": "^2",
      "type": "build"
    },
    {
      "name": "@types/node",
      "type": "build"
    },
    {
      "name": "@typescript-eslint/eslint-plugin",
      "version": "^6",
      "type": "build"
    },
    {
      "name": "@typescript-eslint/parser",
      "version": "^6",
      "type": "build"
    },
    {
      "name": "cdklabs-projen-project-types",
      "type": "build"
    },
    {
      "name": "constructs",
      "version": "^10.0.0",
      "type": "build"
    },
    {
      "name": "eslint",
      "type": "build"
    },
    {
      "name": "eslint-config-prettier",
      "type": "build"
    },
    {
      "name": "eslint-plugin-import",
      "type": "build"
    },
    {
      "name": "eslint-plugin-prettier",
      "type": "build"
    },
    {
      "name": "node-fetch",
      "version": "^2",
      "type": "build"
    },
    {
      "name": "nx",
      "type": "build"
    },
    {
      "name": "prettier",
      "type": "build"
    },
    {
      "name": "projen",
      "type": "build"
    },
    {
      "name": "ts-node",
      "type": "build"
    },
    {
      "name": "typescript",
      "type": "build"
    }
  ],
  "//": "~~ Generated by projen. To modify, edit .projenrc.ts and run \"npx projen\"."
}
